gridnet/VERSION
gridnet/__init__.py
gridnet/py.typed
pygridnet-0.0.0.dev0.dist-info/LICENSE
pygridnet-0.0.0.dev0.dist-info/METADATA
pygridnet-0.0.0.dev0.dist-info/WHEEL
pygridnet-0.0.0.dev0.dist-info/top_level.txt
pygridnet-0.0.0.dev0.dist-info/RECORD
