Metadata-Version: 2.1
Name: pygridnet
Version: 0.0.0.dev0
Summary: A python library to create simple power grid and calculate powerflow.
Author-email: Yan Zhang <dev.claude.yan.zhang@gmail.com>
License: MIT License
Project-URL: Homepage, https://github.com/claudezss/gridnet
Project-URL: Bug Tracker, https://gitlab.com/claudezss/gridnet/-/issues
Keywords: python,power system,power grid,powerflow,machine learning
Classifier: Development Status :: 3 - Alpha
Classifier: Programming Language :: Python :: 3
Classifier: License :: OSI Approved :: MIT License
Classifier: Operating System :: OS Independent
Classifier: Topic :: Software Development :: Libraries
Requires-Python: >=3.11
License-File: LICENSE
Requires-Dist: pandas
Requires-Dist: numpy
Provides-Extra: dev
Requires-Dist: pre-commit; extra == "dev"
Provides-Extra: doc
Requires-Dist: wheel; extra == "doc"
Requires-Dist: mkdocs-material; extra == "doc"
Requires-Dist: mknotebooks; extra == "doc"
Requires-Dist: matplotlib; extra == "doc"
Requires-Dist: notebook; extra == "doc"
Provides-Extra: test
Requires-Dist: pytest; extra == "test"
Requires-Dist: pytest-cov; extra == "test"
